youtubetomp3download/__init__.py
youtubetomp3download-0.7.dist-info/LICENSE
youtubetomp3download-0.7.dist-info/METADATA
youtubetomp3download-0.7.dist-info/WHEEL
youtubetomp3download-0.7.dist-info/top_level.txt
youtubetomp3download-0.7.dist-info/RECORD
