Metadata-Version: 2.1
Name: youtubetomp3download
Version: 0.7
Summary: This package is used to download mp3 from youtube url
Author: Harikrishnan Viswanath
Author-email: hari154542@gmail.com
Classifier: Programming Language :: Python :: 3
Classifier: License :: OSI Approved :: MIT License
Classifier: Operating System :: OS Independent
License-File: LICENSE
Requires-Dist: pytube
